html_dsl/__init__.py
html_dsl/common.py
html_dsl/elements.py
html_dsl-0.5.0.dist-info/METADATA
html_dsl-0.5.0.dist-info/WHEEL
html_dsl-0.5.0.dist-info/RECORD
