Metadata-Version: 2.1
Name: html_dsl
Version: 0.5.0
Summary: A HTML-DSL for Python
Home-page: https://github.com/duyixian1234/html_dsl
License: MIT
Author: duyixian
Author-email: duyixian1234@qq.com
Requires-Python: >=3.8,<4.0
Classifier: License :: OSI Approved :: MIT License
Classifier: Programming Language :: Python :: 3
Classifier: Programming Language :: Python :: 3.8
Classifier: Programming Language :: Python :: 3.9
Classifier: Programming Language :: Python :: 3.10
Classifier: Programming Language :: Python :: 3.11
Classifier: Programming Language :: Python :: 3.12
Project-URL: Repository, https://github.com/duyixian1234/html_dsl
